datpro/__init__.py
datpro/datpro.py
datpro-1.1.7.dist-info/LICENSE
datpro-1.1.7.dist-info/METADATA
datpro-1.1.7.dist-info/WHEEL
datpro-1.1.7.dist-info/RECORD
