Metadata-Version: 2.3
Name: datpro
Version: 1.1.7
Summary: EDA
License: MIT
Author: Dongchun Chen, Ismail (Husain) Bhinderwala, Jingyuan Wang
Requires-Python: >=3.10
Classifier: License :: OSI Approved :: MIT License
Classifier: Programming Language :: Python :: 3
Classifier: Programming Language :: Python :: 3.10
Classifier: Programming Language :: Python :: 3.11
Classifier: Programming Language :: Python :: 3.12
Classifier: Programming Language :: Python :: 3.13
Requires-Dist: altair (>=5.5.0,<6.0.0)
Requires-Dist: ipython (>=8.31.0,<9.0.0)
Requires-Dist: matplotlib (>=3.4.3)
Requires-Dist: pandas (>=2.2.3,<3.0.0)
Requires-Dist: wordcloud (>=1.9.4,<2.0.0)
